README.rst
setup.py
cloudns/__init__.py
cloudns/base.py
cloudns/cli_logic.py
cloudns/cli_utils.py
cloudns/httpclient.py
cloudns/main.py
cloudns/record.py
cloudns/repl.py
cloudns/user.py
cloudns/utils.py
cloudns/zone.py
cloudns.egg-info/PKG-INFO
cloudns.egg-info/SOURCES.txt
cloudns.egg-info/dependency_links.txt
cloudns.egg-info/entry_points.txt
cloudns.egg-info/requires.txt
cloudns.egg-info/top_level.txt