Metadata-Version: 1.1
Name: cloudns
Version: 1.1.1.3
Summary: YY cloudns API python client
Home-page: https://pypi.python.org/pypi/cloudns
Author: Yuanle Song
Author-email: g-yygame-brd@yy.com
License: Artistic License or GPLv2+
Platform: UNKNOWN
Classifier: Development Status :: 3 - Alpha
Classifier: Intended Audience :: Developers
Classifier: License :: OSI Approved :: Artistic License
Classifier: License :: OSI Approved :: GNU General Public License (GPL)
Classifier: License :: OSI Approved :: GNU General Public License v2 or later (GPLv2+)
Classifier: Operating System :: OS Independent
Classifier: Topic :: Software Development :: Libraries
Classifier: Programming Language :: Python :: 2.6
Classifier: Programming Language :: Python :: 2.7
Classifier: Programming Language :: Python :: 3.3
